power_cogs/__init__.py
power_cogs/base/__init__.py
power_cogs/base/base.py
power_cogs/base/torch/__init__.py
power_cogs/base/torch/base_torch_dataset.py
power_cogs/base/torch/base_torch_model.py
power_cogs/base/torch/base_torch_trainer.py
power_cogs/callbacks/__init__.py
power_cogs/callbacks/callback.py
power_cogs/callbacks/class_method_callback.py
power_cogs/callbacks/logger_callback.py
power_cogs/callbacks/save_checkpoint_callback.py
power_cogs/callbacks/tensorboard_callback.py
power_cogs/cluster/__init__.py
power_cogs/cluster/cluster.py
power_cogs/cluster/local_cluster.py
power_cogs/cluster/ray_cluster.py
power_cogs/cluster/execution/__init__.py
power_cogs/cluster/execution/execution.py
power_cogs/cluster/execution/function_execution.py
power_cogs/cluster/execution/rollout_execution.py
power_cogs/config/__init__.py
power_cogs/config/cluster_config.py
power_cogs/config/config.py
power_cogs/config/logging_config.py
power_cogs/config/trainer_config.py
power_cogs/config/tune_config.py
power_cogs/config/torch/__init__.py
power_cogs/config/torch/torch_config.py
power_cogs/examples/__init__.py
power_cogs/examples/mnist/__init__.py
power_cogs/examples/mnist/config.py
power_cogs/examples/mnist/mnist_dataset.py
power_cogs/examples/mnist/mnist_model.py
power_cogs/examples/mnist/mnist_trainer.py
power_cogs/examples/reinforce/__init__.py
power_cogs/examples/reinforce/mlp_agent.py
power_cogs/examples/reinforce/reinforce_trainer.py
power_cogs/logging/__init__.py
power_cogs/logging/logger_utils.py
power_cogs/logging/tensorboard_logger.py
power_cogs/logging/wandb_logger.py
power_cogs/rl/__init__.py
power_cogs/rl/agent.py
power_cogs/rl/env.py
power_cogs/rl/replay_buffer.py
power_cogs/rl/rollout.py
power_cogs/rl/rollout_execution.py
power_cogs/rl/gym/__init__.py
power_cogs/rl/gym/gym_agent.py
power_cogs/rl/gym/gym_rollout_execution.py
power_cogs/rl/gym/torch_gym_agent.py
power_cogs/utils/__init__.py
power_cogs/utils/dict_utils.py
power_cogs/utils/torch_utils.py
power_cogs-0.4.5.dist-info/LICENSE
power_cogs-0.4.5.dist-info/METADATA
power_cogs-0.4.5.dist-info/WHEEL
power_cogs-0.4.5.dist-info/top_level.txt
power_cogs-0.4.5.dist-info/RECORD
